aiq/plugins/mysql/__init__.py
aiq/plugins/mysql/mysql_object_store.py
aiq/plugins/mysql/object_store.py
aiq/plugins/mysql/register.py
aiqtoolkit_mysql-1.2.0a20250806.dist-info/METADATA
aiqtoolkit_mysql-1.2.0a20250806.dist-info/WHEEL
aiqtoolkit_mysql-1.2.0a20250806.dist-info/entry_points.txt
aiqtoolkit_mysql-1.2.0a20250806.dist-info/top_level.txt
aiqtoolkit_mysql-1.2.0a20250806.dist-info/RECORD
