Metadata-Version: 2.4
Name: aiqtoolkit-mysql
Version: 1.2.0a20250806
Summary: Subpackage for MySQL-based object store integration in AIQ toolkit
Keywords: ai,agents,memory,data store
Classifier: Programming Language :: Python
Requires-Python: >=3.12
Requires-Dist: aiqtoolkit==v1.2.0a20250806
Requires-Dist: aiomysql>=0.2.0
